miros/__init__.py
miros/activeobject.py
miros/event.py
miros/foreign.py
miros/hsm.py
miros/singleton.py
miros-2.0.4.dist-info/DESCRIPTION.rst
miros-2.0.4.dist-info/METADATA
miros-2.0.4.dist-info/RECORD
miros-2.0.4.dist-info/WHEEL
miros-2.0.4.dist-info/metadata.json
miros-2.0.4.dist-info/top_level.txt
