Metadata-Version: 2.0
Name: miros
Version: 2.0.4
Summary: A statechart library for Python
Home-page: https://github.com/aleph2c/miros
Author: Scott Volk
Author-email: scottvolk@gmail.com
License: Python 3.5 license
